<map>
<!-- Base KotF kit include file -->
<!-- Created by mameBT -->
<!-- Version 2025.05.13-1 -->
<include id="conquest"/>
<constants fallback="true">
    <constant id="respawn-timer">2s</constant>
    <constant id="score">200</constant>
    <constant id="flag-respawn-timer">18s</constant>
    <constant id="announce-post-pickup">false</constant>
</constants>
<gamemode>kotf</gamemode>
<kits>
    <kit id="base-kit-compass" parent="base-kit">
        <item slot="3" material="compass"/>
    </kit>
    <kit id="flag-kit-no-slowness" force="true">
        <action>
            <replace-item>
                <find unbreakable="true" enchantment="projectile_protection:3" material="chainmail leggings"/>
                <replace unbreakable="true" enchantment="projectile_protection:2" material="chainmail leggings"/>
            </replace-item>
        </action>
        <max-health>8</max-health>
        <if min-server-version="1.9">
            <effect>glowing</effect>
        </if>
        <effect duration="3s" amplifier="2">absorption</effect>
    </kit>
    <kit id="flag-kit" force="true" parent="flag-kit-no-slowness">
        <effect>slowness</effect>
    </kit>
    <kit id="reset-health" force="true">
        <action>
            <replace-item>
                <find unbreakable="true" enchantment="projectile_protection:2" material="chainmail leggings"/>
                <replace unbreakable="true" enchantment="projectile_protection:3" material="chainmail leggings"/>
            </replace-item>
        </action>
        <max-health>20</max-health>
        <if min-server-version="1.9">
            <effect duration="0s" amplifier="0">glowing</effect>
        </if>
        <effect duration="0s" amplifier="0">slowness</effect>
        <effect duration="2s" amplifier="10">regeneration</effect>
        <action>
            <switch-scope inner="match">
                <switch-scope inner="player" filter="all(alive,not(flag-carrier))">
                    <kit>
                        <effect duration="4s" amplifier="3">regeneration</effect>
                    </kit>
                </switch-scope>
            </switch-scope>
        </action>
    </kit>
</kits>
<filters>
    <any id="has-flag">
        <carrying-flag id="flag-carrier">flag</carrying-flag>
        <not>
            <same-team>
                <filter id="flag-carrier"/>
            </same-team>
        </not>
    </any>
    <deny id="deny-flag-carrier">
        <filter id="flag-carrier"/>
    </deny>
</filters>
<compass show-distance="true">
    <player filter="flag-carrier" show-player="true" name="Flag Carrier"/>
</compass>
<score>
    <limit>${score}</limit>
</score>
<toolrepair>
    <tool>compass</tool>
</toolrepair>
<itemkeep>
    <item>compass</item>
</itemkeep>
<respawn spectate="true">
    <message>
        {"translate":"death.respawn.confirmed.waiting.flagDropped"}
    </message>
</respawn>
</map>
